{
  "vpn": {
    "type": "site-to-site",
    "encryption": "AES-256",
    "authentication": {
      "method": "pre-shared key",
      "key": "your-secure-key-here"
    },
    "tunnel_settings": {
      "local_site": {
        "ip_address": "192.168.1.1",
        "subnet": "192.168.1.0/24"
      },
      "remote_site": {
        "ip_address": "192.168.2.1",
        "subnet": "192.168.2.0/24"
      },
      "keepalive": {
        "enabled": true,
        "interval": "30 seconds",
        "timeout": "120 seconds"
      }
    },
    "description": "Site-to-site VPN configuration for secure communication between remote sites."
  }
}
